<Time>06/15/2022 5:41:40 AM</Time>
<Message>
    <Id>986505742741811200</Id>
    <Content>Just really take this as a learning experience, and move forward and be the officer we know. This strike doesn’t mean you can’t activate, just a simple warning to you and let’s the command team know that you have been warned for this.</Content>
</Message>
<Author>
    <Id>731299937186480178</Id>
    <Username>mjkdamdaniel</Username>
    <Discriminator>1156</Discriminator>
</Author>
<Channel>
    <Id>986503683145625600</Id>
    <Name>ticket-0075</Name>
</Channel>